prodigy_iaa/__init__.py
prodigy_iaa/measures.py
prodigy_iaa/processors.py
prodigy_iaa/recipe.py
prodigy_iaa/render.py
prodigy_iaa-0.1.1.dist-info/METADATA
prodigy_iaa-0.1.1.dist-info/WHEEL
prodigy_iaa-0.1.1.dist-info/entry_points.txt
prodigy_iaa-0.1.1.dist-info/RECORD
