Metadata-Version: 2.1
Name: prodigy-iaa
Version: 0.1.1
Summary: 
Author: Peter Baumgartner
Author-email: 5107405+pmbaumgartner@users.noreply.github.com
Requires-Python: >=3.8,<4.0
Classifier: Programming Language :: Python :: 3
Classifier: Programming Language :: Python :: 3.8
Classifier: Programming Language :: Python :: 3.9
Classifier: Programming Language :: Python :: 3.10
Classifier: Programming Language :: Python :: 3.11
